ChangeLog
LICENSE
MANIFEST.in
README
TODO
setup.py
docs/API.txt
docs/FEATURES.txt
docs/HISTORY.txt
docs/INSTALL.txt
docs/PRELUDE.txt
docs/USAGE.txt
examples/async_demo.tac
examples/original_sync_api/SporeAPIExamples.py
txSpore.egg-info/PKG-INFO
txSpore.egg-info/SOURCES.txt
txSpore.egg-info/dependency_links.txt
txSpore.egg-info/top_level.txt
txspore/__init__.py
txspore/client.py
txspore/exception.py
txspore/meta.py
txspore/model.py
txspore/original/SporeAPICoreUtils.py
txspore/original/__init__.py
txspore/testing/__init__.py
txspore/testing/base.py
txspore/testing/payload.py
txspore/testing/suite.py
txspore/tests/__init__.py
txspore/tests/test_client.py
txspore/tests/test_model.py
txspore/tests/test_util.py
txspore/url/__init__.py
txspore/url/atom.py
txspore/url/data.py
txspore/url/rest.py
txspore/util/__init__.py
txspore/util/dist.py