Metadata-Version: 1.0
Name: txSpore
Version: 0.0.2
Summary: An asynchronous Spore Python API using Twisted.
Home-page: http://launchpad.net/txspore
Author: Duncan McGreggor
Author-email: oubiwann@adytum.us
License: MIT
Platform: UNKNOWN
Classifier: Development Status :: 4 - Beta
Classifier: Intended Audience :: Developers
Classifier: Programming Language :: Python
